{"produtos": [{"nome": "Base Alta Cobertura FPS45 - Base Alta Cobertura FPS 45 Cor 2", "ean": "7895389148190"}, {"nome": "M\u00e1scara Facial Purificante Charcoal Mask", "ean": "7895389146516"}, {"nome": "L\u00e1pis para Olhos Super Black", "ean": "7895389126341"}, {"nome": "Photoage Water FPS 50", "ean": "7895389157376"}, {"nome": "M\u00e1scara Facial Hidratante Caviar Gold Mask", "ean": "7895389144222"}, {"nome": "Compose Cal\u00eandula e Hamam\u00e9lis", "ean": "7895389160604"}, {"nome": "M\u00e1scara Facial Antiacne Secatriz Prebio Mask", "ean": "7895389153200"}, {"nome": "Revicare Dry Conditioner", "ean": "7895389160093"}, {"nome": "Photoage Wet FPS 40", "ean": "7895389156966"}, {"nome": "Peel Off Clarify Mask - M\u00e1scara Facial Clareadora Pell Off Clarify Mask", "ean": "7895389140477"}, {"nome": "Creme Hidratante Preventivo de Estrias Preventin", "ean": "7895389401370"}, {"nome": "Revicare Detox - Shampoo Anti res\u00edduo Revicare Charcoal", "ean": "7895389153385"}, {"nome": "Pincel Chanfrado", "ean": "7895389300109"}, {"nome": "Hyaluage Shower Gel - Gel de banho", "ean": "7895389159219"}, {"nome": "Hyaluage Body Hidratante corporal com \u00c1cido Hialur\u00f4nico", "ean": "7895389152517"}, {"nome": "Revox Intense Retinol - Anti-idade e Antirugas", "ean": "7895389159653"}, {"nome": "BK Compact FPS 60 | FPUVA 44 refil 8g - BK Compact FPS 60 cor 1 (claro) refil 8g", "ean": "7895389160628"}, {"nome": "Photoage Mousse FPS 50 - Claro", "ean": "7895389141979"}, {"nome": "Blush Iluminador - Peach Mineral", "ean": "7895389160789"}, {"nome": "Protetor Solar BB Cream FPS80 - BB Cream FPS 80", "ean": "7895389138795"}, {"nome": "Hidratante CB-2 Dermagreen", "ean": "7895389160864"}, {"nome": "M\u00e1scara Facial de Limpeza  Bubble Charcoal Mask", "ean": "7895389153712"}, {"nome": "Hidratante para o Banho Hidrashower", "ean": "7895389116434"}, {"nome": "Concentrado Antioxidante Ineout Resvino", "ean": "7895389142631"}, {"nome": "Base Oil Free FPS 30 - BASE OIL FREE FPS 30 COR 1", "ean": "7895389160277"}, {"nome": "Balm Hidratante Regenerage Face", "ean": "7895389138368"}, {"nome": "Sabonete Hibisco Dermagreen", "ean": "7895389160901"}, {"nome": "Shampoo Fortalecedor Revicare Repair", "ean": "7895389151398"}, {"nome": "T\u00f4nico Glycolique Daily Peel", "ean": "7895389156485"}, {"nome": "Improve C20 S\u00e9rum 30g - Improve C 20 S\u00e9rum Vitamina C - 30g", "ean": "7895389153040"}, {"nome": "Shampoo Anticaspa Revitrat OP", "ean": "7895389137859"}, {"nome": "Cover Blend FPS 60 - Cor B - 4,5g", "ean": "7895389161625"}, {"nome": "Booster LIFT - S\u00e9rum firmador 15ml", "ean": "7895389161014"}, {"nome": "L\u00e1pis para Sobrancelhas Highlight Maxi", "ean": "7895389128918"}, {"nome": "Secatriz Lo\u00e7\u00e3o Secativa - Lo\u00e7\u00e3o T\u00f4nica Rosada Secatriz Secativa", "ean": "7895389277890"}, {"nome": "M\u00e1scara Facial Antioleosidade Clear Mask", "ean": "7895389145670"}, {"nome": "M\u00e1scara para C\u00edlios Extreme Cils", "ean": "7895389136296"}, {"nome": "Hyaluage Lipup Stick - 3,5g", "ean": "7895389160840"}, {"nome": "Hyaluage \u00c1gua Micelar 120mL", "ean": "7895389160871"}, {"nome": "S\u00e9rum Clareador Clarit\u00e9 Olhos CC", "ean": "7895389119985"}, {"nome": "Lo\u00e7\u00e3o T\u00f4nica Facial  Secatriz Oil Control", "ean": "7895389403497"}, {"nome": "M\u00e1scara Facial Calmante Green Mask", "ean": "7895389150865"}, {"nome": "Creme de Massagem Drencell", "ean": "7895389151619"}, {"nome": "Improve C 20 Antioxidante Facial", "ean": "7895389125511"}, {"nome": "Desodorante Antitranspirante Senskin Deo", "ean": "7895389139549"}, {"nome": "Ineout Collagen Gummies", "ean": "7895389160390"}, {"nome": "Hidratante Corporal Ureiactive", "ean": "7895389341379"}, {"nome": "Desodorante antitranspirante Senskin Deo Cal\u00eandula", "ean": "7895389151671"}, {"nome": "M\u00e1scara Esfoliante Compose Gommage", "ean": "7895389136050"}, {"nome": "Booster PIC - S\u00e9rum antioxidante 15ml", "ean": "7895389161038"}, {"nome": "Revitrat Antiqueda - Shampoo Antiqueda Revitrat", "ean": "7895389137873"}, {"nome": "Gel Creme Anti-idade Age Inverse Nanoage", "ean": "7895389120189"}, {"nome": "M\u00e1scara Hidratante Intensiva para P\u00e9s Foot Mask", "ean": "7895389151169"}, {"nome": "REFIL PHOTOAGE CC POWDER FPS63 - PHOTOAGE CC POWDER FPS 63 - COR 2 REFIL(CLARO)", "ean": "7895389157321"}, {"nome": "M\u00e1scara Facial Anti-idade Collagen Mask", "ean": "7895389140514"}, {"nome": "Improve Corpo - Hidratante Corporal", "ean": "7895389348613"}, {"nome": "Lifting Instant\u00e2neo Age Away - 4 sach\u00eas", "ean": "7895389143782"}, {"nome": "Base Fortalecedora para Unhas Nail Force", "ean": "7895389131079"}, {"nome": "Shampoo de Limpeza Profunda Revicare Micelar", "ean": "7895389151459"}, {"nome": "Hidratante Iluminador Delifresh", "ean": "7895389143065"}, {"nome": "Gel Creme Clareador Clarit\u00e9 Cysteamin", "ean": "7895389155600"}, {"nome": "M\u00e1scara Restauradora Revicare Power Mask", "ean": "7895389154580"}, {"nome": "Compose Lo\u00e7\u00e3o - Lo\u00e7\u00e3o T\u00f4nica Facial para Peles Sens\u00edveis Compose", "ean": "7895389138412"}, {"nome": "Improve C 30 Antioxidante e Anti-Envelhecimento Facial", "ean": "7895389145489"}, {"nome": "Face Fusion Contour & Bronzer", "ean": "7895389160802"}, {"nome": "Compose Hidracare", "ean": "7895389160833"}, {"nome": "Base Oil Free FPS 30 - Bege m\u00e9dio dourado", "ean": "7895389150360"}, {"nome": "Batom Extreme Color - Lovely New", "ean": "7895389160734"}, {"nome": "Paleta Eyebrow Essentials", "ean": "7895389160963"}, {"nome": "Gel Creme Anti-idade Age Inverse Night Repair", "ean": "7895389145076"}, {"nome": "Age Inverse Olhos - Gel Creme Anti-idade para os Olhos Age Inverse", "ean": "7895389124804"}, {"nome": "Protetor Solar Corporal Photoage Corpo FPS 50", "ean": "7895389117813"}, {"nome": "M\u00e1scara Facial Noturna Water Sleeping Mask", "ean": "7895389150216"}, {"nome": "Photoage MAX FPS 99 - Protetor Solar Facial Photoage Max FPS 99", "ean": "7895389136661"}, {"nome": "Concentrado Vitam\u00ednico e Mineral Ineout Force", "ean": "7895389138511"}, {"nome": "Photoage Stick Color FPS 99 cor B claro", "ean": "7895389154627"}, {"nome": "Suplemento Nutricional com Col\u00e1geno Ineout Collagen Age", "ean": "7895389138771"}, {"nome": "Compose Camomila e Azuleno - Sabonete Facial L\u00edquido Compose Camomila & Azuleno", "ean": "7895389122879"}, {"nome": "ESTOJO PARA P\u00d3 COMPACTO", "ean": "7895389160314"}, {"nome": "Improve C Acqua Bruma Hidratante", "ean": "7895389145472"}, {"nome": "BB Cream Capilar - Multifuncional Capilar", "ean": "7895389134551"}, {"nome": "Hidratante para M\u00e3os  BB Hand FPS 15", "ean": "7895389149470"}, {"nome": "S\u00e9rum Phyto Retinol Dermagreen", "ean": "7895389160895"}, {"nome": "Hyaluage Acqua Bomb", "ean": "7895389158755"}, {"nome": "Iluminador em P\u00f3 Lumi\u00e9re", "ean": "7895389160956"}, {"nome": "L\u00e1pis Secativo Secatriz", "ean": "7895389100341"}, {"nome": "Refil P\u00f3 Compacto e Protetor Solar Block Compact Mineral FPS 50 - Refil Block Compact - Claro", "ean": "7895389157277"}, {"nome": "Improve C 20 S\u00e9rum 15g - Improve C 20 S\u00e9rum - Vitamina C - 15G", "ean": "7895389157093"}, {"nome": "Photoage Mineral Fluido  FPS 50 - 50ml - Cor m\u00e9dio", "ean": "7895389126181"}, {"nome": "Glycolique Sabonete", "ean": "7895389158748"}, {"nome": "Secatriz Acne Spot 15G", "ean": "7895389160888"}, {"nome": "Revox Olhos - Concentrado Anti-idade", "ean": "7895389144475"}, {"nome": "Creme Antiestrias Striactive", "ean": "7895389118629"}, {"nome": "Vinocare Acqua 150 ml", "ean": "7895389156645"}, {"nome": "Protetor Solar Facial Photoage Fluido Antiox FPS 60", "ean": "7895389121933"}, {"nome": "Spray Anticelulite Drencell Booster Redutor", "ean": "7895389144666"}, {"nome": "Clarit\u00e9 S\u00e9rum - S\u00e9rum Clareador Clarit\u00e9 TX", "ean": "7895389131857"}, {"nome": "\u00d3leo multifuncional Vinocare Oil", "ean": "7895389153637"}, {"nome": "Hyaluage Olhos Creme para \u00e1rea dos olhos", "ean": "7895389156539"}, {"nome": "Photoage Water Color FPS 60", "ean": "7895389160246"}, {"nome": "Compose Camomila", "ean": "7895389160970"}, {"nome": "Sabonete em Barra Secatriz", "ean": "7895389765212"}, {"nome": "Sabonete L\u00edquido Secatriz Salic", "ean": "7895389145410"}, {"nome": "Shampoo Revicare Prolumi - Shampoo Iluminador Revicare Prolumi", "ean": "7895389151329"}, {"nome": "Improve C 30 S\u00e9rum", "ean": "7895389159585"}, {"nome": "Improve C 10 S\u00e9rum 15g de Vitamina C", "ean": "7895389157109"}, {"nome": "M\u00e1scara Revicare Repair - M\u00e1scara Fortalecedora Hidratante Revicare Repair", "ean": "7895389151428"}, {"nome": "Booster NIA - S\u00e9rum antioleosidade 15ml", "ean": "7895389161021"}, {"nome": "M\u00e1scara Facial Antioxidante Resveratrol e Berry Mask", "ean": "7895389153804"}, {"nome": "M\u00e1scara Revicare Prolumi - M\u00e1scara Iluminadora Prolumi", "ean": "7895389151367"}, {"nome": "Balm Corporal Regenerage Body", "ean": "7895389156683"}, {"nome": "Shampoo Anticaspa Revitrat ZN", "ean": "7895389137866"}, {"nome": "Improve C T\u00f4nico Facial", "ean": "7895389159028"}, {"nome": "M\u00e1scara Hidratante para os P\u00e9s Foot Mask - Bisnaga", "ean": "7895389150995"}, {"nome": "Compose Mousse - Espuma de Limpeza Facial", "ean": "7895389131932"}, {"nome": "Photoage Stick Incolor FPS 99", "ean": "7895389160826"}, {"nome": "M\u00e1scara Facial Revigorante Detox Mask", "ean": "7895389140491"}, {"nome": "Improve Night Repair", "ean": "7895389150810"}, {"nome": "Age Inverse Resculp - S\u00e9rum Remodelador Facial - S\u00e9rum Remodelador Facial Age Resculp", "ean": "7895389126655"}, {"nome": "Hyaluage Acqua Bruma Hidratante", "ean": "7895389156522"}, {"nome": "Hidratante Facial Secatriz Prebio Control", "ean": "7895389148138"}, {"nome": "Glycolique Intense Peel", "ean": "7895389157833"}, {"nome": "S\u00e9rum Fortalecedor de C\u00edlios e Sobrancelhas Eyelash Power", "ean": "7895389131727"}, {"nome": "Sabonete L\u00edquido Secatriz", "ean": "7895389273151"}, {"nome": "S\u00e9rum Clareador Anti-idade Clarit\u00e9 AG+ Peel", "ean": "7895389126150"}, {"nome": "Revicare Dry Shampoo", "ean": "7895389156867"}, {"nome": "Deo Colonia L'eau D'amie", "ean": "7895389137552"}, {"nome": "Improve C 10 S\u00e9rum Vitamina C - 30g", "ean": "7895389142020"}, {"nome": "Protetor Solar Facial Photoage Antiox Color FPS 60", "ean": "7895389126730"}, {"nome": "Hyaluage Complex HA5 S\u00e9rum \u00c1cido Hialur\u00f4nico", "ean": "7895389146448"}, {"nome": "Base Liquid Powder FPS 45 - Base L\u00edquida Liquid Powder FPS 45 Cor 1", "ean": "7895389136708"}], "precos": [{"id": "<class 'ulid.ULID'>", "ean_id": "7895389148190", "loja_id": 1, "preco": "R$196,00", "datahora": "10/01/2023 - 15:49:35"}, {"id": "<class 'ulid.ULID'>", "ean_id": "7895389146516", "loja_id": 1, "preco": "R$17,90", "datahora": "10/01/2023 - 15:49:35"}, {"id": "<class 'ulid.ULID'>", "ean_id": "7895389126341", "loja_id": 1, "preco": "R$85,00", "datahora": "10/01/2023 - 15:49:36"}, {"id": "<class 'ulid.ULID'>", "ean_id": "7895389157376", "loja_id": 1, "preco": "R$84,60", "datahora": "10/01/2023 - 15:49:36"}, {"id": "<class 'ulid.ULID'>", "ean_id": "7895389144222", "loja_id": 1, "preco": "R$18,90", "datahora": "10/01/2023 - 15:49:36"}, {"id": "<class 'ulid.ULID'>", "ean_id": "7895389160604", "loja_id": 1, "preco": "R$84,90", "datahora": "10/01/2023 - 15:49:37"}, {"id": "<class 'ulid.ULID'>", "ean_id": "7895389153200", "loja_id": 1, "preco": "R$18,90", "datahora": "10/01/2023 - 15:49:37"}, {"id": "<class 'ulid.ULID'>", "ean_id": "7895389160093", "loja_id": 1, "preco": "R$69,90", "datahora": "10/01/2023 - 15:49:38"}, {"id": "<class 'ulid.ULID'>", "ean_id": "7895389156966", "loja_id": 1, "preco": "R$62,91", "datahora": "10/01/2023 - 15:49:39"}, {"id": "<class 'ulid.ULID'>", "ean_id": "7895389140477", "loja_id": 1, "preco": "R$16,90", "datahora": "10/01/2023 - 15:49:40"}, {"id": "<class 'ulid.ULID'>", "ean_id": "7895389401370", "loja_id": 1, "preco": "R$175,00", "datahora": "10/01/2023 - 15:49:41"}, {"id": "<class 'ulid.ULID'>", "ean_id": "7895389153385", "loja_id": 1, "preco": "R$69,90", "datahora": "10/01/2023 - 15:49:41"}, {"id": "<class 'ulid.ULID'>", "ean_id": "7895389300109", "loja_id": 1, "preco": "R$72,00", "datahora": "10/01/2023 - 15:49:42"}, {"id": "<class 'ulid.ULID'>", "ean_id": "7895389159219", "loja_id": 1, "preco": "R$60,90", "datahora": "10/01/2023 - 15:49:42"}, {"id": "<class 'ulid.ULID'>", "ean_id": "7895389152517", "loja_id": 1, "preco": "R$106,00", "datahora": "10/01/2023 - 15:49:43"}, {"id": "<class 'ulid.ULID'>", "ean_id": "7895389159653", "loja_id": 1, "preco": "R$262,90", "datahora": "10/01/2023 - 15:49:43"}, {"id": "<class 'ulid.ULID'>", "ean_id": "7895389160628", "loja_id": 1, "preco": "R$125,91", "datahora": "10/01/2023 - 15:49:44"}, {"id": "<class 'ulid.ULID'>", "ean_id": "7895389141979", "loja_id": 1, "preco": "R$116,10", "datahora": "10/01/2023 - 15:49:44"}, {"id": "<class 'ulid.ULID'>", "ean_id": "7895389160789", "loja_id": 1, "preco": "R$119,90", "datahora": "10/01/2023 - 15:49:45"}, {"id": "<class 'ulid.ULID'>", "ean_id": "7895389138795", "loja_id": 1, "preco": "R$122,31", "datahora": "10/01/2023 - 15:49:46"}, {"id": "<class 'ulid.ULID'>", "ean_id": "7895389160864", "loja_id": 1, "preco": "R$139,00", "datahora": "10/01/2023 - 15:49:47"}, {"id": "<class 'ulid.ULID'>", "ean_id": "7895389153712", "loja_id": 1, "preco": "R$18,50", "datahora": "10/01/2023 - 15:49:47"}, {"id": "<class 'ulid.ULID'>", "ean_id": "7895389116434", "loja_id": 1, "preco": "R$119,00", "datahora": "10/01/2023 - 15:49:48"}, {"id": "<class 'ulid.ULID'>", "ean_id": "7895389142631", "loja_id": 1, "preco": "R$147,00", "datahora": "10/01/2023 - 15:49:49"}, {"id": "<class 'ulid.ULID'>", "ean_id": "7895389160277", "loja_id": 1, "preco": "R$195,00", "datahora": "10/01/2023 - 15:49:49"}, {"id": "<class 'ulid.ULID'>", "ean_id": "7895389138368", "loja_id": 1, "preco": "R$76,50", "datahora": "10/01/2023 - 15:49:49"}, {"id": "<class 'ulid.ULID'>", "ean_id": "7895389160901", "loja_id": 1, "preco": "R$69,90", "datahora": "10/01/2023 - 15:49:51"}, {"id": "<class 'ulid.ULID'>", "ean_id": "7895389151398", "loja_id": 1, "preco": "R$49,90", "datahora": "10/01/2023 - 15:49:51"}, {"id": "<class 'ulid.ULID'>", "ean_id": "7895389156485", "loja_id": 1, "preco": "R$129,90", "datahora": "10/01/2023 - 15:49:52"}, {"id": "<class 'ulid.ULID'>", "ean_id": "7895389153040", "loja_id": 1, "preco": "R$269,90", "datahora": "10/01/2023 - 15:49:52"}, {"id": "<class 'ulid.ULID'>", "ean_id": "7895389137859", "loja_id": 1, "preco": "R$99,90", "datahora": "10/01/2023 - 15:49:53"}, {"id": "<class 'ulid.ULID'>", "ean_id": "7895389161625", "loja_id": 1, "preco": "R$119,00", "datahora": "10/01/2023 - 15:49:53"}, {"id": "<class 'ulid.ULID'>", "ean_id": "7895389161014", "loja_id": 1, "preco": "R$71,94", "datahora": "10/01/2023 - 15:49:54"}, {"id": "<class 'ulid.ULID'>", "ean_id": "7895389128918", "loja_id": 1, "preco": "R$105,00", "datahora": "10/01/2023 - 15:49:54"}, {"id": "<class 'ulid.ULID'>", "ean_id": "7895389277890", "loja_id": 1, "preco": "R$129,90", "datahora": "10/01/2023 - 15:49:55"}, {"id": "<class 'ulid.ULID'>", "ean_id": "7895389145670", "loja_id": 1, "preco": "R$17,90", "datahora": "10/01/2023 - 15:49:55"}, {"id": "<class 'ulid.ULID'>", "ean_id": "7895389136296", "loja_id": 1, "preco": "R$119,00", "datahora": "10/01/2023 - 15:49:56"}, {"id": "<class 'ulid.ULID'>", "ean_id": "7895389160840", "loja_id": 1, "preco": "R$105,00", "datahora": "10/01/2023 - 15:49:57"}, {"id": "<class 'ulid.ULID'>", "ean_id": "7895389160871", "loja_id": 1, "preco": "R$39,90", "datahora": "10/01/2023 - 15:49:57"}, {"id": "<class 'ulid.ULID'>", "ean_id": "7895389119985", "loja_id": 1, "preco": "R$228,00", "datahora": "10/01/2023 - 15:49:58"}, {"id": "<class 'ulid.ULID'>", "ean_id": "7895389403497", "loja_id": 1, "preco": "R$129,90", "datahora": "10/01/2023 - 15:49:58"}, {"id": "<class 'ulid.ULID'>", "ean_id": "7895389150865", "loja_id": 1, "preco": "R$16,90", "datahora": "10/01/2023 - 15:49:59"}, {"id": "<class 'ulid.ULID'>", "ean_id": "7895389151619", "loja_id": 1, "preco": "R$198,00", "datahora": "10/01/2023 - 15:50:00"}, {"id": "<class 'ulid.ULID'>", "ean_id": "7895389125511", "loja_id": 1, "preco": "R$269,90", "datahora": "10/01/2023 - 15:50:00"}, {"id": "<class 'ulid.ULID'>", "ean_id": "7895389139549", "loja_id": 1, "preco": "R$54,90", "datahora": "10/01/2023 - 15:50:00"}, {"id": "<class 'ulid.ULID'>", "ean_id": "7895389160390", "loja_id": 1, "preco": "R$239,00", "datahora": "10/01/2023 - 15:50:01"}, {"id": "<class 'ulid.ULID'>", "ean_id": "7895389341379", "loja_id": 1, "preco": "R$155,00", "datahora": "10/01/2023 - 15:50:01"}, {"id": "<class 'ulid.ULID'>", "ean_id": "7895389151671", "loja_id": 1, "preco": "R$59,00", "datahora": "10/01/2023 - 15:50:02"}, {"id": "<class 'ulid.ULID'>", "ean_id": "7895389136050", "loja_id": 1, "preco": "R$124,90", "datahora": "10/01/2023 - 15:50:02"}, {"id": "<class 'ulid.ULID'>", "ean_id": "7895389161038", "loja_id": 1, "preco": "R$71,94", "datahora": "10/01/2023 - 15:50:03"}, {"id": "<class 'ulid.ULID'>", "ean_id": "7895389137873", "loja_id": 1, "preco": "R$94,90", "datahora": "10/01/2023 - 15:50:03"}, {"id": "<class 'ulid.ULID'>", "ean_id": "7895389120189", "loja_id": 1, "preco": "R$309,90", "datahora": "10/01/2023 - 15:50:04"}, {"id": "<class 'ulid.ULID'>", "ean_id": "7895389151169", "loja_id": 1, "preco": "R$16,90", "datahora": "10/01/2023 - 15:50:04"}, {"id": "<class 'ulid.ULID'>", "ean_id": "7895389157321", "loja_id": 1, "preco": "R$118,80", "datahora": "10/01/2023 - 15:50:05"}, {"id": "<class 'ulid.ULID'>", "ean_id": "7895389140514", "loja_id": 1, "preco": "R$17,90", "datahora": "10/01/2023 - 15:50:07"}, {"id": "<class 'ulid.ULID'>", "ean_id": "7895389348613", "loja_id": 1, "preco": "R$144,00", "datahora": "10/01/2023 - 15:50:07"}, {"id": "<class 'ulid.ULID'>", "ean_id": "7895389143782", "loja_id": 1, "preco": "R$64,90", "datahora": "10/01/2023 - 15:50:07"}, {"id": "<class 'ulid.ULID'>", "ean_id": "7895389131079", "loja_id": 1, "preco": "R$49,90", "datahora": "10/01/2023 - 15:50:08"}, {"id": "<class 'ulid.ULID'>", "ean_id": "7895389151459", "loja_id": 1, "preco": "R$69,90", "datahora": "10/01/2023 - 15:50:08"}, {"id": "<class 'ulid.ULID'>", "ean_id": "7895389143065", "loja_id": 1, "preco": "R$75,00", "datahora": "10/01/2023 - 15:50:09"}, {"id": "<class 'ulid.ULID'>", "ean_id": "7895389155600", "loja_id": 1, "preco": "R$264,90", "datahora": "10/01/2023 - 15:50:09"}, {"id": "<class 'ulid.ULID'>", "ean_id": "7895389154580", "loja_id": 1, "preco": "R$109,90", "datahora": "10/01/2023 - 15:50:10"}, {"id": "<class 'ulid.ULID'>", "ean_id": "7895389138412", "loja_id": 1, "preco": "R$119,90", "datahora": "10/01/2023 - 15:50:10"}, {"id": "<class 'ulid.ULID'>", "ean_id": "7895389145489", "loja_id": 1, "preco": "R$329,90", "datahora": "10/01/2023 - 15:50:11"}, {"id": "<class 'ulid.ULID'>", "ean_id": "7895389160802", "loja_id": 1, "preco": "R$154,90", "datahora": "10/01/2023 - 15:50:11"}, {"id": "<class 'ulid.ULID'>", "ean_id": "7895389160833", "loja_id": 1, "preco": "R$135,90", "datahora": "10/01/2023 - 15:50:12"}, {"id": "<class 'ulid.ULID'>", "ean_id": "7895389150360", "loja_id": 1, "preco": "R$195,00", "datahora": "10/01/2023 - 15:50:13"}, {"id": "<class 'ulid.ULID'>", "ean_id": "7895389160734", "loja_id": 1, "preco": "R$89,90", "datahora": "10/01/2023 - 15:50:14"}, {"id": "<class 'ulid.ULID'>", "ean_id": "7895389160963", "loja_id": 1, "preco": "R$229,00", "datahora": "10/01/2023 - 15:50:15"}, {"id": "<class 'ulid.ULID'>", "ean_id": "7895389145076", "loja_id": 1, "preco": "R$309,90", "datahora": "10/01/2023 - 15:50:15"}, {"id": "<class 'ulid.ULID'>", "ean_id": "7895389124804", "loja_id": 1, "preco": "R$241,90", "datahora": "10/01/2023 - 15:50:16"}, {"id": "<class 'ulid.ULID'>", "ean_id": "7895389117813", "loja_id": 1, "preco": "R$89,10", "datahora": "10/01/2023 - 15:50:17"}, {"id": "<class 'ulid.ULID'>", "ean_id": "7895389150216", "loja_id": 1, "preco": "R$18,90", "datahora": "10/01/2023 - 15:50:18"}, {"id": "<class 'ulid.ULID'>", "ean_id": "7895389136661", "loja_id": 1, "preco": "R$107,91", "datahora": "10/01/2023 - 15:50:18"}, {"id": "<class 'ulid.ULID'>", "ean_id": "7895389138511", "loja_id": 1, "preco": "R$131,90", "datahora": "10/01/2023 - 15:50:18"}, {"id": "<class 'ulid.ULID'>", "ean_id": "7895389154627", "loja_id": 1, "preco": "R$137,61", "datahora": "10/01/2023 - 15:50:19"}, {"id": "<class 'ulid.ULID'>", "ean_id": "7895389138771", "loja_id": 1, "preco": "R$185,90", "datahora": "10/01/2023 - 15:50:21"}, {"id": "<class 'ulid.ULID'>", "ean_id": "7895389122879", "loja_id": 1, "preco": "R$98,90", "datahora": "10/01/2023 - 15:50:21"}, {"id": "<class 'ulid.ULID'>", "ean_id": "7895389160314", "loja_id": 1, "preco": "R$64,90", "datahora": "10/01/2023 - 15:50:21"}, {"id": "<class 'ulid.ULID'>", "ean_id": "7895389145472", "loja_id": 1, "preco": "R$66,90", "datahora": "10/01/2023 - 15:50:22"}, {"id": "<class 'ulid.ULID'>", "ean_id": "7895389134551", "loja_id": 1, "preco": "R$98,91", "datahora": "10/01/2023 - 15:50:23"}, {"id": "<class 'ulid.ULID'>", "ean_id": "7895389149470", "loja_id": 1, "preco": "R$108,00", "datahora": "10/01/2023 - 15:50:23"}, {"id": "<class 'ulid.ULID'>", "ean_id": "7895389160895", "loja_id": 1, "preco": "R$199,90", "datahora": "10/01/2023 - 15:50:24"}, {"id": "<class 'ulid.ULID'>", "ean_id": "7895389158755", "loja_id": 1, "preco": "R$139,00", "datahora": "10/01/2023 - 15:50:24"}, {"id": "<class 'ulid.ULID'>", "ean_id": "7895389160956", "loja_id": 1, "preco": "R$139,90", "datahora": "10/01/2023 - 15:50:25"}, {"id": "<class 'ulid.ULID'>", "ean_id": "7895389100341", "loja_id": 1, "preco": "R$79,90", "datahora": "10/01/2023 - 15:50:25"}, {"id": "<class 'ulid.ULID'>", "ean_id": "7895389157277", "loja_id": 1, "preco": "R$145,00", "datahora": "10/01/2023 - 15:50:26"}, {"id": "<class 'ulid.ULID'>", "ean_id": "7895389157093", "loja_id": 1, "preco": "R$159,90", "datahora": "10/01/2023 - 15:50:26"}, {"id": "<class 'ulid.ULID'>", "ean_id": "7895389126181", "loja_id": 1, "preco": "R$125,10", "datahora": "10/01/2023 - 15:50:27"}, {"id": "<class 'ulid.ULID'>", "ean_id": "7895389158748", "loja_id": 1, "preco": "R$75,00", "datahora": "10/01/2023 - 15:50:28"}, {"id": "<class 'ulid.ULID'>", "ean_id": "7895389160888", "loja_id": 1, "preco": "R$79,90", "datahora": "10/01/2023 - 15:50:29"}, {"id": "<class 'ulid.ULID'>", "ean_id": "7895389144475", "loja_id": 1, "preco": "R$219,90", "datahora": "10/01/2023 - 15:50:29"}, {"id": "<class 'ulid.ULID'>", "ean_id": "7895389118629", "loja_id": 1, "preco": "R$323,00", "datahora": "10/01/2023 - 15:50:30"}, {"id": "<class 'ulid.ULID'>", "ean_id": "7895389156645", "loja_id": 1, "preco": "R$65,90", "datahora": "10/01/2023 - 15:50:30"}, {"id": "<class 'ulid.ULID'>", "ean_id": "7895389121933", "loja_id": 1, "preco": "R$116,10", "datahora": "10/01/2023 - 15:50:31"}, {"id": "<class 'ulid.ULID'>", "ean_id": "7895389144666", "loja_id": 1, "preco": "R$208,00", "datahora": "10/01/2023 - 15:50:31"}, {"id": "<class 'ulid.ULID'>", "ean_id": "7895389131857", "loja_id": 1, "preco": "R$189,90", "datahora": "10/01/2023 - 15:50:32"}, {"id": "<class 'ulid.ULID'>", "ean_id": "7895389153637", "loja_id": 1, "preco": "R$118,00", "datahora": "10/01/2023 - 15:50:32"}, {"id": "<class 'ulid.ULID'>", "ean_id": "7895389156539", "loja_id": 1, "preco": "R$169,90", "datahora": "10/01/2023 - 15:50:33"}, {"id": "<class 'ulid.ULID'>", "ean_id": "7895389160246", "loja_id": 1, "preco": "R$89,10", "datahora": "10/01/2023 - 15:50:33"}, {"id": "<class 'ulid.ULID'>", "ean_id": "7895389160970", "loja_id": 1, "preco": "R$84,90", "datahora": "10/01/2023 - 15:50:34"}, {"id": "<class 'ulid.ULID'>", "ean_id": "7895389765212", "loja_id": 1, "preco": "R$30,50", "datahora": "10/01/2023 - 15:50:34"}, {"id": "<class 'ulid.ULID'>", "ean_id": "7895389145410", "loja_id": 1, "preco": "R$49,90", "datahora": "10/01/2023 - 15:50:35"}, {"id": "<class 'ulid.ULID'>", "ean_id": "7895389151329", "loja_id": 1, "preco": "R$49,90", "datahora": "10/01/2023 - 15:50:35"}, {"id": "<class 'ulid.ULID'>", "ean_id": "7895389159585", "loja_id": 1, "preco": "R$329,90", "datahora": "10/01/2023 - 15:50:36"}, {"id": "<class 'ulid.ULID'>", "ean_id": "7895389157109", "loja_id": 1, "preco": "R$119,90", "datahora": "10/01/2023 - 15:50:36"}, {"id": "<class 'ulid.ULID'>", "ean_id": "7895389151428", "loja_id": 1, "preco": "R$69,90", "datahora": "10/01/2023 - 15:50:37"}, {"id": "<class 'ulid.ULID'>", "ean_id": "7895389161021", "loja_id": 1, "preco": "R$65,94", "datahora": "10/01/2023 - 15:50:37"}, {"id": "<class 'ulid.ULID'>", "ean_id": "7895389153804", "loja_id": 1, "preco": "R$16,90", "datahora": "10/01/2023 - 15:50:37"}, {"id": "<class 'ulid.ULID'>", "ean_id": "7895389151367", "loja_id": 1, "preco": "R$69,90", "datahora": "10/01/2023 - 15:50:38"}, {"id": "<class 'ulid.ULID'>", "ean_id": "7895389156683", "loja_id": 1, "preco": "R$100,00", "datahora": "10/01/2023 - 15:50:38"}, {"id": "<class 'ulid.ULID'>", "ean_id": "7895389137866", "loja_id": 1, "preco": "R$99,90", "datahora": "10/01/2023 - 15:50:39"}, {"id": "<class 'ulid.ULID'>", "ean_id": "7895389159028", "loja_id": 1, "preco": "R$139,00", "datahora": "10/01/2023 - 15:50:39"}, {"id": "<class 'ulid.ULID'>", "ean_id": "7895389150995", "loja_id": 1, "preco": "R$67,90", "datahora": "10/01/2023 - 15:50:40"}, {"id": "<class 'ulid.ULID'>", "ean_id": "7895389131932", "loja_id": 1, "preco": "R$108,90", "datahora": "10/01/2023 - 15:50:40"}, {"id": "<class 'ulid.ULID'>", "ean_id": "7895389160826", "loja_id": 1, "preco": "R$137,61", "datahora": "10/01/2023 - 15:50:41"}, {"id": "<class 'ulid.ULID'>", "ean_id": "7895389140491", "loja_id": 1, "preco": "R$17,90", "datahora": "10/01/2023 - 15:50:42"}, {"id": "<class 'ulid.ULID'>", "ean_id": "7895389150810", "loja_id": 1, "preco": "R$249,90", "datahora": "10/01/2023 - 15:50:42"}, {"id": "<class 'ulid.ULID'>", "ean_id": "7895389126655", "loja_id": 1, "preco": "R$296,90", "datahora": "10/01/2023 - 15:50:42"}, {"id": "<class 'ulid.ULID'>", "ean_id": "7895389156522", "loja_id": 1, "preco": "R$63,90", "datahora": "10/01/2023 - 15:50:43"}, {"id": "<class 'ulid.ULID'>", "ean_id": "7895389148138", "loja_id": 1, "preco": "R$95,00", "datahora": "10/01/2023 - 15:50:44"}, {"id": "<class 'ulid.ULID'>", "ean_id": "7895389157833", "loja_id": 1, "preco": "R$249,90", "datahora": "10/01/2023 - 15:50:44"}, {"id": "<class 'ulid.ULID'>", "ean_id": "7895389131727", "loja_id": 1, "preco": "R$126,00", "datahora": "10/01/2023 - 15:50:46"}, {"id": "<class 'ulid.ULID'>", "ean_id": "7895389273151", "loja_id": 1, "preco": "R$79,90", "datahora": "10/01/2023 - 15:50:46"}, {"id": "<class 'ulid.ULID'>", "ean_id": "7895389126150", "loja_id": 1, "preco": "R$249,90", "datahora": "10/01/2023 - 15:50:46"}, {"id": "<class 'ulid.ULID'>", "ean_id": "7895389156867", "loja_id": 1, "preco": "R$69,90", "datahora": "10/01/2023 - 15:50:47"}, {"id": "<class 'ulid.ULID'>", "ean_id": "7895389137552", "loja_id": 1, "preco": "R$169,90", "datahora": "10/01/2023 - 15:50:47"}, {"id": "<class 'ulid.ULID'>", "ean_id": "7895389142020", "loja_id": 1, "preco": "R$219,00", "datahora": "10/01/2023 - 15:50:48"}, {"id": "<class 'ulid.ULID'>", "ean_id": "7895389126730", "loja_id": 1, "preco": "R$116,10", "datahora": "10/01/2023 - 15:50:48"}, {"id": "<class 'ulid.ULID'>", "ean_id": "7895389146448", "loja_id": 1, "preco": "R$239,90", "datahora": "10/01/2023 - 15:50:49"}, {"id": "<class 'ulid.ULID'>", "ean_id": "7895389136708", "loja_id": 1, "preco": "R$189,00", "datahora": "10/01/2023 - 15:50:49"}], "lojas": [{"id": 1, "nome": "Dermage", "site": "htttps://www.dermage.com.br"}]}