{"produtos": [{"nome": "Glycolique Sabonete", "ean": "7895389158748"}, {"nome": "Hyaluage Lipup Stick - 3,5g", "ean": "7895389160840"}, {"nome": "REFIL PHOTOAGE CC POWDER FPS63 - PHOTOAGE CC POWDER FPS 63 - COR 2 REFIL(CLARO)", "ean": "7895389157321"}, {"nome": "Photoage Water FPS 50", "ean": "7895389157376"}, {"nome": "M\u00e1scara Facial Calmante Green Mask", "ean": "7895389150865"}, {"nome": "Spray Anticelulite Drencell Booster Redutor", "ean": "7895389144666"}, {"nome": "Compose Camomila", "ean": "7895389160970"}, {"nome": "Creme Hidratante Preventivo de Estrias Preventin", "ean": "7895389401370"}, {"nome": "M\u00e1scara Facial Anti-idade Collagen Mask", "ean": "7895389140514"}, {"nome": "M\u00e1scara Revicare Prolumi - M\u00e1scara Iluminadora Prolumi", "ean": "7895389151367"}, {"nome": "Compose Cal\u00eandula e Hamam\u00e9lis", "ean": "7895389160604"}, {"nome": "Protetor Solar Facial Photoage Fluido Antiox FPS 60", "ean": "7895389121933"}, {"nome": "BK Compact FPS 60 | FPUVA 44 refil 8g - BK Compact FPS 60 cor 1 (claro) refil 8g", "ean": "7895389160628"}, {"nome": "M\u00e1scara Hidratante Intensiva para P\u00e9s Foot Mask", "ean": "7895389151169"}, {"nome": "Base Fortalecedora para Unhas Nail Force", "ean": "7895389131079"}, {"nome": "Pincel Chanfrado", "ean": "7895389300109"}, {"nome": "Booster LIFT - S\u00e9rum firmador 15ml", "ean": "7895389161014"}, {"nome": "Hyaluage \u00c1gua Micelar 120mL", "ean": "7895389160871"}, {"nome": "M\u00e1scara para C\u00edlios Extreme Cils", "ean": "7895389136296"}, {"nome": "Peel Off Clarify Mask - M\u00e1scara Facial Clareadora Pell Off Clarify Mask", "ean": "7895389140477"}, {"nome": "Creme de Massagem Drencell", "ean": "7895389151619"}, {"nome": "Hidratante para M\u00e3os  BB Hand FPS 15", "ean": "7895389149470"}, {"nome": "Shampoo Anticaspa Revitrat ZN", "ean": "7895389137866"}, {"nome": "M\u00e1scara Facial Noturna Water Sleeping Mask", "ean": "7895389150216"}, {"nome": "Revicare Dry Shampoo", "ean": "7895389156867"}, {"nome": "Base Alta Cobertura FPS45 - Base Alta Cobertura FPS 45 Cor 2", "ean": "7895389148190"}, {"nome": "Secatriz Acne Spot 15G", "ean": "7895389160888"}, {"nome": "Desodorante Antitranspirante Senskin Deo", "ean": "7895389139549"}, {"nome": "Booster PIC - S\u00e9rum antioxidante 15ml", "ean": "7895389161038"}, {"nome": "Hidratante Corporal Ureiactive", "ean": "7895389341379"}, {"nome": "Age Inverse Olhos - Gel Creme Anti-idade para os Olhos Age Inverse", "ean": "7895389124804"}, {"nome": "Improve C 30 Antioxidante e Anti-Envelhecimento Facial", "ean": "7895389145489"}, {"nome": "Protetor Solar Facial Photoage Antiox Color FPS 60", "ean": "7895389126730"}, {"nome": "Shampoo de Limpeza Profunda Revicare Micelar", "ean": "7895389151459"}, {"nome": "M\u00e1scara Facial Antiacne Secatriz Prebio Mask", "ean": "7895389153200"}, {"nome": "Hyaluage Olhos Creme para \u00e1rea dos olhos", "ean": "7895389156539"}, {"nome": "Base Liquid Powder FPS 45 - Base L\u00edquida Liquid Powder FPS 45 Cor 1", "ean": "7895389136708"}, {"nome": "Revitrat Antiqueda - Shampoo Antiqueda Revitrat", "ean": "7895389137873"}, {"nome": "Protetor Solar Corporal Photoage Corpo FPS 50", "ean": "7895389117813"}, {"nome": "Hyaluage Acqua Bruma Hidratante", "ean": "7895389156522"}, {"nome": "Compose Hidracare", "ean": "7895389160833"}, {"nome": "Improve C 20 Antioxidante Facial", "ean": "7895389125511"}, {"nome": "Paleta Eyebrow Essentials", "ean": "7895389160963"}, {"nome": "Revicare Detox - Shampoo Anti res\u00edduo Revicare Charcoal", "ean": "7895389153385"}, {"nome": "Revox Intense Retinol - Anti-idade e Antirugas", "ean": "7895389159653"}, {"nome": "Photoage Stick Incolor FPS 99", "ean": "7895389160826"}, {"nome": "M\u00e1scara Facial Antioleosidade Clear Mask", "ean": "7895389145670"}, {"nome": "Lifting Instant\u00e2neo Age Away - 4 sach\u00eas", "ean": "7895389143782"}, {"nome": "S\u00e9rum Clareador Anti-idade Clarit\u00e9 AG+ Peel", "ean": "7895389126150"}, {"nome": "Photoage Mineral Fluido  FPS 50 - 50ml - Cor m\u00e9dio", "ean": "7895389126181"}, {"nome": "Refil P\u00f3 Compacto e Protetor Solar Block Compact Mineral FPS 50 - Refil Block Compact - Claro", "ean": "7895389157277"}, {"nome": "Hyaluage Body Hidratante corporal com \u00c1cido Hialur\u00f4nico", "ean": "7895389152517"}, {"nome": "Suplemento Nutricional com Col\u00e1geno Ineout Collagen Age", "ean": "7895389138771"}, {"nome": "M\u00e1scara Hidratante para os P\u00e9s Foot Mask - Bisnaga", "ean": "7895389150995"}, {"nome": "M\u00e1scara Facial Hidratante Caviar Gold Mask", "ean": "7895389144222"}, {"nome": "M\u00e1scara Facial Purificante Charcoal Mask", "ean": "7895389146516"}, {"nome": "Age Inverse Resculp - S\u00e9rum Remodelador Facial - S\u00e9rum Remodelador Facial Age Resculp", "ean": "7895389126655"}, {"nome": "Improve C 10 S\u00e9rum 15g de Vitamina C", "ean": "7895389157109"}, {"nome": "Improve C 20 S\u00e9rum 15g - Improve C 20 S\u00e9rum - Vitamina C - 15G", "ean": "7895389157093"}, {"nome": "Revox Olhos - Concentrado Anti-idade", "ean": "7895389144475"}, {"nome": "Photoage Wet FPS 40", "ean": "7895389156966"}, {"nome": "Base Oil Free FPS 30 - BASE OIL FREE FPS 30 COR 1", "ean": "7895389160277"}, {"nome": "Blush Iluminador - Peach Mineral", "ean": "7895389160789"}, {"nome": "Base Oil Free FPS 30 - Bege m\u00e9dio dourado", "ean": "7895389150360"}, {"nome": "\u00d3leo multifuncional Vinocare Oil", "ean": "7895389153637"}, {"nome": "Sabonete L\u00edquido Secatriz Salic", "ean": "7895389145410"}, {"nome": "Sabonete em Barra Secatriz", "ean": "7895389765212"}, {"nome": "M\u00e1scara Restauradora Revicare Power Mask", "ean": "7895389154580"}, {"nome": "Hidratante CB-2 Dermagreen", "ean": "7895389160864"}, {"nome": "Shampoo Revicare Prolumi - Shampoo Iluminador Revicare Prolumi", "ean": "7895389151329"}, {"nome": "Hyaluage Shower Gel - Gel de banho", "ean": "7895389159219"}, {"nome": "Photoage Water Color FPS 60", "ean": "7895389160246"}, {"nome": "Gel Creme Anti-idade Age Inverse Night Repair", "ean": "7895389145076"}, {"nome": "BB Cream Capilar - Multifuncional Capilar", "ean": "7895389134551"}, {"nome": "Clarit\u00e9 S\u00e9rum - S\u00e9rum Clareador Clarit\u00e9 TX", "ean": "7895389131857"}, {"nome": "Compose Camomila e Azuleno - Sabonete Facial L\u00edquido Compose Camomila & Azuleno", "ean": "7895389122879"}, {"nome": "Sabonete Hibisco Dermagreen", "ean": "7895389160901"}, {"nome": "Improve C20 S\u00e9rum 30g - Improve C 20 S\u00e9rum Vitamina C - 30g", "ean": "7895389153040"}, {"nome": "Improve C 10 S\u00e9rum Vitamina C - 30g", "ean": "7895389142020"}, {"nome": "Batom Extreme Color - Lovely New", "ean": "7895389160734"}, {"nome": "Compose Mousse - Espuma de Limpeza Facial", "ean": "7895389131932"}, {"nome": "M\u00e1scara Revicare Repair - M\u00e1scara Fortalecedora Hidratante Revicare Repair", "ean": "7895389151428"}, {"nome": "Photoage Mousse FPS 50 - Claro", "ean": "7895389141979"}, {"nome": "L\u00e1pis para Sobrancelhas Highlight Maxi", "ean": "7895389128918"}, {"nome": "Hidratante para o Banho Hidrashower", "ean": "7895389116434"}, {"nome": "Photoage MAX FPS 99 - Protetor Solar Facial Photoage Max FPS 99", "ean": "7895389136661"}, {"nome": "L\u00e1pis Secativo Secatriz", "ean": "7895389100341"}, {"nome": "S\u00e9rum Fortalecedor de C\u00edlios e Sobrancelhas Eyelash Power", "ean": "7895389131727"}, {"nome": "Revicare Dry Conditioner", "ean": "7895389160093"}, {"nome": "Hidratante Facial Secatriz Prebio Control", "ean": "7895389148138"}, {"nome": "M\u00e1scara Esfoliante Compose Gommage", "ean": "7895389136050"}, {"nome": "Improve C 30 S\u00e9rum", "ean": "7895389159585"}, {"nome": "Secatriz Lo\u00e7\u00e3o Secativa - Lo\u00e7\u00e3o T\u00f4nica Rosada Secatriz Secativa", "ean": "7895389277890"}, {"nome": "M\u00e1scara Facial Revigorante Detox Mask", "ean": "7895389140491"}, {"nome": "Face Fusion Contour & Bronzer", "ean": "7895389160802"}, {"nome": "ESTOJO PARA P\u00d3 COMPACTO", "ean": "7895389160314"}, {"nome": "S\u00e9rum Phyto Retinol Dermagreen", "ean": "7895389160895"}, {"nome": "Glycolique Intense Peel", "ean": "7895389157833"}, {"nome": "Gel Creme Clareador Clarit\u00e9 Cysteamin", "ean": "7895389155600"}, {"nome": "Improve C T\u00f4nico Facial", "ean": "7895389159028"}, {"nome": "Compose Lo\u00e7\u00e3o - Lo\u00e7\u00e3o T\u00f4nica Facial para Peles Sens\u00edveis Compose", "ean": "7895389138412"}, {"nome": "Improve Night Repair", "ean": "7895389150810"}, {"nome": "Improve C Acqua Bruma Hidratante", "ean": "7895389145472"}, {"nome": "Lo\u00e7\u00e3o T\u00f4nica Facial  Secatriz Oil Control", "ean": "7895389403497"}, {"nome": "Iluminador em P\u00f3 Lumi\u00e9re", "ean": "7895389160956"}, {"nome": "Hyaluage Acqua Bomb", "ean": "7895389158755"}, {"nome": "Vinocare Acqua 150 ml", "ean": "7895389156645"}, {"nome": "L\u00e1pis para Olhos Super Black", "ean": "7895389126341"}, {"nome": "T\u00f4nico Glycolique Daily Peel", "ean": "7895389156485"}, {"nome": "Improve Corpo - Hidratante Corporal", "ean": "7895389348613"}, {"nome": "Gel Creme Anti-idade Age Inverse Nanoage", "ean": "7895389120189"}, {"nome": "Sabonete L\u00edquido Secatriz", "ean": "7895389273151"}, {"nome": "M\u00e1scara Facial Antioxidante Resveratrol e Berry Mask", "ean": "7895389153804"}, {"nome": "Creme Antiestrias Striactive", "ean": "7895389118629"}, {"nome": "Hidratante Iluminador Delifresh", "ean": "7895389143065"}, {"nome": "Balm Corporal Regenerage Body", "ean": "7895389156683"}, {"nome": "Shampoo Fortalecedor Revicare Repair", "ean": "7895389151398"}, {"nome": "Booster NIA - S\u00e9rum antioleosidade 15ml", "ean": "7895389161021"}, {"nome": "Shampoo Anticaspa Revitrat OP", "ean": "7895389137859"}, {"nome": "S\u00e9rum Clareador Clarit\u00e9 Olhos CC", "ean": "7895389119985"}, {"nome": "Ineout Collagen Gummies", "ean": "7895389160390"}, {"nome": "Photoage Stick Color FPS 99 cor B claro", "ean": "7895389154627"}, {"nome": "Deo Colonia L'eau D'amie", "ean": "7895389137552"}, {"nome": "Protetor Solar BB Cream FPS80 - BB Cream FPS 80", "ean": "7895389138795"}, {"nome": "Concentrado Vitam\u00ednico e Mineral Ineout Force", "ean": "7895389138511"}, {"nome": "Hyaluage Complex HA5 S\u00e9rum \u00c1cido Hialur\u00f4nico", "ean": "7895389146448"}, {"nome": "Desodorante antitranspirante Senskin Deo Cal\u00eandula", "ean": "7895389151671"}, {"nome": "Concentrado Antioxidante Ineout Resvino", "ean": "7895389142631"}, {"nome": "Balm Hidratante Regenerage Face", "ean": "7895389138368"}, {"nome": "M\u00e1scara Facial de Limpeza  Bubble Charcoal Mask", "ean": "7895389153712"}, {"nome": "Cover Blend FPS 60 - Cor B - 4,5g", "ean": "7895389161625"}], "precos": [{"id": "01GPXR8MMT5PYZQ229Z44PBSP3", "ean_id": "7895389158748", "loja_id": 1, "preco": "R$67,50", "datahora": "16/01/2023 - 13:58:09"}, {"id": "01GPXR8Q07MK84T1VR9AFEVS1T", "ean_id": "7895389160840", "loja_id": 1, "preco": "R$105,00", "datahora": "16/01/2023 - 13:58:11"}, {"id": "01GPXR8QCAXD0N6AFAZKTZJ32S", "ean_id": "7895389157321", "loja_id": 1, "preco": "R$132,00", "datahora": "16/01/2023 - 13:58:12"}, {"id": "01GPXR8QQXC32DJH6R3PWE9ZYR", "ean_id": "7895389157376", "loja_id": 1, "preco": "R$94,00", "datahora": "16/01/2023 - 13:58:12"}, {"id": "01GPXR8RDKQVERNMD6812GQT14", "ean_id": "7895389150865", "loja_id": 1, "preco": "R$16,90", "datahora": "16/01/2023 - 13:58:13"}, {"id": "01GPXR8RWWSRV6K8X7JW68ZFEA", "ean_id": "7895389144666", "loja_id": 1, "preco": "R$208,00", "datahora": "16/01/2023 - 13:58:13"}, {"id": "01GPXR8SG0MJ1SVE172N7Z9F4S", "ean_id": "7895389160970", "loja_id": 1, "preco": "R$84,90", "datahora": "16/01/2023 - 13:58:14"}, {"id": "01GPXR8SV6NKMF5KNA1YP672VS", "ean_id": "7895389401370", "loja_id": 1, "preco": "R$175,00", "datahora": "16/01/2023 - 13:58:14"}, {"id": "01GPXR8TBAYEF1JS1MJEFG0JT9", "ean_id": "7895389140514", "loja_id": 1, "preco": "R$12,53", "datahora": "16/01/2023 - 13:58:15"}, {"id": "01GPXR8TYW4EDAAGEK4R2FPTYV", "ean_id": "7895389151367", "loja_id": 1, "preco": "R$69,90", "datahora": "16/01/2023 - 13:58:15"}, {"id": "01GPXR8WPZQW2TGKWB3BPCV34S", "ean_id": "7895389160604", "loja_id": 1, "preco": "R$84,90", "datahora": "16/01/2023 - 13:58:17"}, {"id": "01GPXR8X45P82X4SV1ED7SKF81", "ean_id": "7895389121933", "loja_id": 1, "preco": "R$103,20", "datahora": "16/01/2023 - 13:58:18"}, {"id": "01GPXR8XN4NXZBTR3ND9N4TV8N", "ean_id": "7895389160628", "loja_id": 1, "preco": "R$139,90", "datahora": "16/01/2023 - 13:58:18"}, {"id": "01GPXR8YNRY379V3CRKTRJ2KV5", "ean_id": "7895389151169", "loja_id": 1, "preco": "R$16,90", "datahora": "16/01/2023 - 13:58:19"}, {"id": "01GPXR8Z5CPCYDCR2632TKAJZA", "ean_id": "7895389131079", "loja_id": 1, "preco": "R$49,90", "datahora": "16/01/2023 - 13:58:20"}, {"id": "01GPXR8ZJK7P28BE5TPSESH0GH", "ean_id": "7895389300109", "loja_id": 1, "preco": "R$72,00", "datahora": "16/01/2023 - 13:58:20"}, {"id": "01GPXR90CTC22EP1JCD73HJQFH", "ean_id": "7895389161014", "loja_id": 1, "preco": "R$119,90", "datahora": "16/01/2023 - 13:58:21"}, {"id": "01GPXR90XEND4HK8EBZWB73HEF", "ean_id": "7895389160871", "loja_id": 1, "preco": "R$39,90", "datahora": "16/01/2023 - 13:58:21"}, {"id": "01GPXR91A8BSZ4WM310FBFQP63", "ean_id": "7895389136296", "loja_id": 1, "preco": "R$119,00", "datahora": "16/01/2023 - 13:58:22"}, {"id": "01GPXR91NSA953KECZ7FTTV0YA", "ean_id": "7895389140477", "loja_id": 1, "preco": "R$16,90", "datahora": "16/01/2023 - 13:58:22"}, {"id": "01GPXR9220HGDN1T5T9FHY40PF", "ean_id": "7895389151619", "loja_id": 1, "preco": "R$198,00", "datahora": "16/01/2023 - 13:58:23"}, {"id": "01GPXR92D93CP7DHKW2RC4KGJ3", "ean_id": "7895389149470", "loja_id": 1, "preco": "R$108,00", "datahora": "16/01/2023 - 13:58:23"}, {"id": "01GPXR92TEDTCMP4B39DXJHNGP", "ean_id": "7895389137866", "loja_id": 1, "preco": "R$99,90", "datahora": "16/01/2023 - 13:58:23"}, {"id": "01GPXR938TG9B8190C98AXP8VP", "ean_id": "7895389150216", "loja_id": 1, "preco": "R$18,90", "datahora": "16/01/2023 - 13:58:24"}, {"id": "01GPXR93SVD8HRVGJK9ZE0DRKZ", "ean_id": "7895389156867", "loja_id": 1, "preco": "R$69,90", "datahora": "16/01/2023 - 13:58:24"}, {"id": "01GPXR94940HAANYF7Q7YF3RP6", "ean_id": "7895389148190", "loja_id": 1, "preco": "R$196,00", "datahora": "16/01/2023 - 13:58:25"}, {"id": "01GPXR94SS8JB50XTA6XKGWNMM", "ean_id": "7895389160888", "loja_id": 1, "preco": "R$71,91", "datahora": "16/01/2023 - 13:58:25"}, {"id": "01GPXR958XSP3AETRRW31H116T", "ean_id": "7895389139549", "loja_id": 1, "preco": "R$54,90", "datahora": "16/01/2023 - 13:58:26"}, {"id": "01GPXR96WJ2HDD6J377YVCATK1", "ean_id": "7895389161038", "loja_id": 1, "preco": "R$119,90", "datahora": "16/01/2023 - 13:58:28"}, {"id": "01GPXR97BJZYX5WGSQTSANJ9N3", "ean_id": "7895389341379", "loja_id": 1, "preco": "R$155,00", "datahora": "16/01/2023 - 13:58:28"}, {"id": "01GPXR97VS9W37P5J9D7Z7Z08F", "ean_id": "7895389124804", "loja_id": 1, "preco": "R$241,90", "datahora": "16/01/2023 - 13:58:29"}, {"id": "01GPXR98F7ZA547F1MGGYEY8F8", "ean_id": "7895389145489", "loja_id": 1, "preco": "R$329,90", "datahora": "16/01/2023 - 13:58:29"}, {"id": "01GPXR993NX2193990NJJBJDSS", "ean_id": "7895389126730", "loja_id": 1, "preco": "R$103,20", "datahora": "16/01/2023 - 13:58:30"}, {"id": "01GPXR99FNTGVBRBSYH0SFQRDK", "ean_id": "7895389151459", "loja_id": 1, "preco": "R$69,90", "datahora": "16/01/2023 - 13:58:30"}, {"id": "01GPXR9A2PMM3K2BNV8NH6XZC7", "ean_id": "7895389153200", "loja_id": 1, "preco": "R$18,90", "datahora": "16/01/2023 - 13:58:31"}, {"id": "01GPXR9AKBAHMJ4X1AS8XY0G9D", "ean_id": "7895389156539", "loja_id": 1, "preco": "R$144,42", "datahora": "16/01/2023 - 13:58:31"}, {"id": "01GPXR9BJ9WJ6CCM8HRQJKY5XD", "ean_id": "7895389136708", "loja_id": 1, "preco": "R$189,00", "datahora": "16/01/2023 - 13:58:32"}, {"id": "01GPXR9CM13RY66TX2XYG0W4V4", "ean_id": "7895389137873", "loja_id": 1, "preco": "R$94,90", "datahora": "16/01/2023 - 13:58:33"}, {"id": "01GPXR9D3N9PK5RDKRBNHHY8J8", "ean_id": "7895389117813", "loja_id": 1, "preco": "R$84,15", "datahora": "16/01/2023 - 13:58:34"}, {"id": "01GPXR9DF808VRVC4640XG81NX", "ean_id": "7895389156522", "loja_id": 1, "preco": "R$44,73", "datahora": "16/01/2023 - 13:58:34"}, {"id": "01GPXR9EM98R0WEA332H8GADGH", "ean_id": "7895389160833", "loja_id": 1, "preco": "R$122,31", "datahora": "16/01/2023 - 13:58:36"}, {"id": "01GPXR9F3YWXERS6J2GZSHM2HE", "ean_id": "7895389125511", "loja_id": 1, "preco": "R$269,90", "datahora": "16/01/2023 - 13:58:36"}, {"id": "01GPXR9FGN8CCCA1B71NQ7PWVB", "ean_id": "7895389160963", "loja_id": 1, "preco": "R$229,00", "datahora": "16/01/2023 - 13:58:36"}, {"id": "01GPXR9GF92S7NBFH9S15PBQPA", "ean_id": "7895389153385", "loja_id": 1, "preco": "R$69,90", "datahora": "16/01/2023 - 13:58:37"}, {"id": "01GPXR9HBGXDBBD9NN9E723ZQ9", "ean_id": "7895389159653", "loja_id": 1, "preco": "R$262,90", "datahora": "16/01/2023 - 13:58:38"}, {"id": "01GPXR9JAAKWREAK4HR9CHAT5J", "ean_id": "7895389160826", "loja_id": 1, "preco": "R$137,61", "datahora": "16/01/2023 - 13:58:39"}, {"id": "01GPXR9JQ0829BP37KJ8S8A5SR", "ean_id": "7895389145670", "loja_id": 1, "preco": "R$17,90", "datahora": "16/01/2023 - 13:58:40"}, {"id": "01GPXR9K8YK1BQQ4WNBZXRWNEG", "ean_id": "7895389143782", "loja_id": 1, "preco": "R$64,90", "datahora": "16/01/2023 - 13:58:40"}, {"id": "01GPXR9KR3H0NE64DVX2HJXJSY", "ean_id": "7895389126150", "loja_id": 1, "preco": "R$249,90", "datahora": "16/01/2023 - 13:58:41"}, {"id": "01GPXR9MC5ZVHGXHDFVR2VSDHV", "ean_id": "7895389126181", "loja_id": 1, "preco": "R$139,00", "datahora": "16/01/2023 - 13:58:41"}, {"id": "01GPXR9MY1GKJFR4611D5YDYMF", "ean_id": "7895389157277", "loja_id": 1, "preco": "R$145,00", "datahora": "16/01/2023 - 13:58:42"}, {"id": "01GPXR9ND2V1YTVEM34EX3NGC6", "ean_id": "7895389152517", "loja_id": 1, "preco": "R$84,80", "datahora": "16/01/2023 - 13:58:42"}, {"id": "01GPXR9NHER9P49D5BGZFVMTTM", "ean_id": "7895389138771", "loja_id": 1, "preco": "R$185,90", "datahora": "16/01/2023 - 13:58:43"}, {"id": "01GPXR9NX5FHVY25HWPMMA5J50", "ean_id": "7895389150995", "loja_id": 1, "preco": "R$67,90", "datahora": "16/01/2023 - 13:58:43"}, {"id": "01GPXR9PDB68QFKF2V13YW6FP5", "ean_id": "7895389144222", "loja_id": 1, "preco": "R$18,90", "datahora": "16/01/2023 - 13:58:44"}, {"id": "01GPXR9PXY21CZ156NFJKTR3AB", "ean_id": "7895389146516", "loja_id": 1, "preco": "R$17,90", "datahora": "16/01/2023 - 13:58:44"}, {"id": "01GPXR9QRPJND3P93R249CMCMH", "ean_id": "7895389126655", "loja_id": 1, "preco": "R$296,90", "datahora": "16/01/2023 - 13:58:45"}, {"id": "01GPXR9R8PRFTZE8W0H5ANTG8Q", "ean_id": "7895389157109", "loja_id": 1, "preco": "R$119,90", "datahora": "16/01/2023 - 13:58:45"}, {"id": "01GPXR9RSSRSGHAZ3K0VHJHK83", "ean_id": "7895389157093", "loja_id": 1, "preco": "R$159,90", "datahora": "16/01/2023 - 13:58:46"}, {"id": "01GPXR9S9E4SMW166Q0Q6NKGXS", "ean_id": "7895389144475", "loja_id": 1, "preco": "R$219,90", "datahora": "16/01/2023 - 13:58:46"}, {"id": "01GPXR9T3NNPX1N0KHFHQSDN07", "ean_id": "7895389156966", "loja_id": 1, "preco": "R$69,90", "datahora": "16/01/2023 - 13:58:47"}, {"id": "01GPXR9TFWHP8BG86RBXEM8C81", "ean_id": "7895389160277", "loja_id": 1, "preco": "R$195,00", "datahora": "16/01/2023 - 13:58:48"}, {"id": "01GPXR9V0NRZ21QVMD9BJMN8J6", "ean_id": "7895389160789", "loja_id": 1, "preco": "R$119,90", "datahora": "16/01/2023 - 13:58:48"}, {"id": "01GPXR9VCW2XV6HFYPBSQ7JD6Z", "ean_id": "7895389150360", "loja_id": 1, "preco": "R$117,00", "datahora": "16/01/2023 - 13:58:49"}, {"id": "01GPXR9VYCGNSXVMNCPVVN698N", "ean_id": "7895389153637", "loja_id": 1, "preco": "R$94,40", "datahora": "16/01/2023 - 13:58:49"}, {"id": "01GPXR9WEDVG48NARHKGCBF0MH", "ean_id": "7895389145410", "loja_id": 1, "preco": "R$42,42", "datahora": "16/01/2023 - 13:58:50"}, {"id": "01GPXR9WVX27D9V61RZVE0ZN6P", "ean_id": "7895389765212", "loja_id": 1, "preco": "R$21,35", "datahora": "16/01/2023 - 13:58:50"}, {"id": "01GPXR9XNSVBY82250MW98Q07S", "ean_id": "7895389154580", "loja_id": 1, "preco": "R$109,90", "datahora": "16/01/2023 - 13:58:51"}, {"id": "01GPXR9Y8QR9YMHGJ0SNP032H7", "ean_id": "7895389160864", "loja_id": 1, "preco": "R$139,00", "datahora": "16/01/2023 - 13:58:52"}, {"id": "01GPXR9Z838A3RSEJHFH8CBGF2", "ean_id": "7895389151329", "loja_id": 1, "preco": "R$49,90", "datahora": "16/01/2023 - 13:58:53"}, {"id": "01GPXRA049G6W50DE09D2D34GD", "ean_id": "7895389159219", "loja_id": 1, "preco": "R$51,76", "datahora": "16/01/2023 - 13:58:53"}, {"id": "01GPXRA0G859XQTZ5R10EK8CZM", "ean_id": "7895389160246", "loja_id": 1, "preco": "R$89,10", "datahora": "16/01/2023 - 13:58:54"}, {"id": "01GPXRA0PTFHGBKJ5SDPJFYSPJ", "ean_id": "7895389145076", "loja_id": 1, "preco": "R$309,90", "datahora": "16/01/2023 - 13:58:54"}, {"id": "01GPXRA19SMV784MCFSRZ3P7C8", "ean_id": "7895389134551", "loja_id": 1, "preco": "R$109,90", "datahora": "16/01/2023 - 13:58:55"}, {"id": "01GPXRA1P6NCGY17XVAC06BYMZ", "ean_id": "7895389131857", "loja_id": 1, "preco": "R$189,90", "datahora": "16/01/2023 - 13:58:55"}, {"id": "01GPXRA26553PT0CRX7XZ7R6PP", "ean_id": "7895389122879", "loja_id": 1, "preco": "R$98,90", "datahora": "16/01/2023 - 13:58:56"}, {"id": "01GPXRA2TQ7384DAYX3FT82PFV", "ean_id": "7895389160901", "loja_id": 1, "preco": "R$69,90", "datahora": "16/01/2023 - 13:58:56"}, {"id": "01GPXRA3ABS21B69Z8B1GS1GVJ", "ean_id": "7895389153040", "loja_id": 1, "preco": "R$269,90", "datahora": "16/01/2023 - 13:58:57"}, {"id": "01GPXRA3TA7JDXEJXTSRVZ1G3R", "ean_id": "7895389142020", "loja_id": 1, "preco": "R$219,00", "datahora": "16/01/2023 - 13:58:57"}, {"id": "01GPXRA4769RNQR0W5PY53FTT9", "ean_id": "7895389160734", "loja_id": 1, "preco": "R$89,90", "datahora": "16/01/2023 - 13:58:58"}, {"id": "01GPXRA5VQ8SZFJ5KMT3ZSBTBT", "ean_id": "7895389131932", "loja_id": 1, "preco": "R$108,90", "datahora": "16/01/2023 - 13:58:59"}, {"id": "01GPXRA67XS8DNCSX2MN99QHMR", "ean_id": "7895389151428", "loja_id": 1, "preco": "R$69,90", "datahora": "16/01/2023 - 13:59:00"}, {"id": "01GPXRA7AHYYAPS17X8SYX3QJA", "ean_id": "7895389141979", "loja_id": 1, "preco": "R$129,00", "datahora": "16/01/2023 - 13:59:01"}, {"id": "01GPXRA7R7WJPSSZSEBKN57WQ9", "ean_id": "7895389128918", "loja_id": 1, "preco": "R$73,50", "datahora": "16/01/2023 - 13:59:01"}, {"id": "01GPXRA84EY1YWQEAFSPRDE0S8", "ean_id": "7895389116434", "loja_id": 1, "preco": "R$119,00", "datahora": "16/01/2023 - 13:59:02"}, {"id": "01GPXRA8MW3Q7YY5ZH0ST209YD", "ean_id": "7895389136661", "loja_id": 1, "preco": "R$119,90", "datahora": "16/01/2023 - 13:59:02"}, {"id": "01GPXRA979XRW29FCARWVT3SET", "ean_id": "7895389100341", "loja_id": 1, "preco": "R$79,90", "datahora": "16/01/2023 - 13:59:03"}, {"id": "01GPXRA9Q83P3Y0C2HYEYGAFNX", "ean_id": "7895389131727", "loja_id": 1, "preco": "R$126,00", "datahora": "16/01/2023 - 13:59:03"}, {"id": "01GPXRAAJKPERPZRMSAM86EG4A", "ean_id": "7895389160093", "loja_id": 1, "preco": "R$69,90", "datahora": "16/01/2023 - 13:59:04"}, {"id": "01GPXRABCC4R8DY7T46NAC2M2T", "ean_id": "7895389148138", "loja_id": 1, "preco": "R$95,00", "datahora": "16/01/2023 - 13:59:05"}, {"id": "01GPXRAC0EW8Z5GRAA35G6ZQ2Y", "ean_id": "7895389136050", "loja_id": 1, "preco": "R$124,90", "datahora": "16/01/2023 - 13:59:06"}, {"id": "01GPXRACH17XMWGFC2KQ329JP6", "ean_id": "7895389159585", "loja_id": 1, "preco": "R$329,90", "datahora": "16/01/2023 - 13:59:06"}, {"id": "01GPXRAD7C5SA28XDZM1TAT34C", "ean_id": "7895389277890", "loja_id": 1, "preco": "R$129,90", "datahora": "16/01/2023 - 13:59:07"}, {"id": "01GPXRADQ7GJYX9VZW6ACG5FTY", "ean_id": "7895389140491", "loja_id": 1, "preco": "R$17,90", "datahora": "16/01/2023 - 13:59:07"}, {"id": "01GPXRAEZ935MVJETD0NTVRCJF", "ean_id": "7895389160802", "loja_id": 1, "preco": "R$154,90", "datahora": "16/01/2023 - 13:59:09"}, {"id": "01GPXRAFC09P2FGC4V2W0N7JS5", "ean_id": "7895389160314", "loja_id": 1, "preco": "R$64,90", "datahora": "16/01/2023 - 13:59:09"}, {"id": "01GPXRAFT1JC1GMTQSDXG6GDHN", "ean_id": "7895389160895", "loja_id": 1, "preco": "R$199,90", "datahora": "16/01/2023 - 13:59:10"}, {"id": "01GPXRAG6QC2PC3M2DP3VZM720", "ean_id": "7895389157833", "loja_id": 1, "preco": "R$174,93", "datahora": "16/01/2023 - 13:59:10"}, {"id": "01GPXRAGJX8VGWKXQ36F2RX604", "ean_id": "7895389155600", "loja_id": 1, "preco": "R$264,90", "datahora": "16/01/2023 - 13:59:10"}, {"id": "01GPXRAH437XT25K2KZ60SMKTK", "ean_id": "7895389159028", "loja_id": 1, "preco": "R$97,30", "datahora": "16/01/2023 - 13:59:11"}, {"id": "01GPXRAHGT4FY97APKR0M3M3FS", "ean_id": "7895389138412", "loja_id": 1, "preco": "R$119,90", "datahora": "16/01/2023 - 13:59:11"}, {"id": "01GPXRAJGQV0ADBAXJ034WX3A2", "ean_id": "7895389150810", "loja_id": 1, "preco": "R$249,90", "datahora": "16/01/2023 - 13:59:12"}, {"id": "01GPXRAJXEB0XKPSA7E07M3K9E", "ean_id": "7895389145472", "loja_id": 1, "preco": "R$66,90", "datahora": "16/01/2023 - 13:59:13"}, {"id": "01GPXRAKD2D747CMDV5X3CXJJ6", "ean_id": "7895389403497", "loja_id": 1, "preco": "R$129,90", "datahora": "16/01/2023 - 13:59:13"}, {"id": "01GPXRAKSPT45E6H4YTTP2PEZ1", "ean_id": "7895389160956", "loja_id": 1, "preco": "R$139,90", "datahora": "16/01/2023 - 13:59:14"}, {"id": "01GPXRAM5XWMRMCCHFP6KD64BT", "ean_id": "7895389158755", "loja_id": 1, "preco": "R$97,30", "datahora": "16/01/2023 - 13:59:14"}, {"id": "01GPXRAMP2T12PK1V4DE3DAM8A", "ean_id": "7895389156645", "loja_id": 1, "preco": "R$56,02", "datahora": "16/01/2023 - 13:59:15"}, {"id": "01GPXRAN7MWWC059C6JCKJZKJZ", "ean_id": "7895389126341", "loja_id": 1, "preco": "R$59,50", "datahora": "16/01/2023 - 13:59:15"}, {"id": "01GPXRANV705CPYG7VA9EAC78K", "ean_id": "7895389156485", "loja_id": 1, "preco": "R$103,92", "datahora": "16/01/2023 - 13:59:16"}, {"id": "01GPXRAP7DP8EXQSFAC17KFK6X", "ean_id": "7895389348613", "loja_id": 1, "preco": "R$144,00", "datahora": "16/01/2023 - 13:59:16"}, {"id": "01GPXRAPQ37BA1CRQX4E0DCZFV", "ean_id": "7895389120189", "loja_id": 1, "preco": "R$309,90", "datahora": "16/01/2023 - 13:59:17"}, {"id": "01GPXRAQ3M61STYFXYXX9SKGMS", "ean_id": "7895389273151", "loja_id": 1, "preco": "R$79,90", "datahora": "16/01/2023 - 13:59:17"}, {"id": "01GPXRAQKM62AYAS7J1F5DMRRW", "ean_id": "7895389153804", "loja_id": 1, "preco": "R$16,90", "datahora": "16/01/2023 - 13:59:18"}, {"id": "01GPXRAR47MNBJT1SG6EGAFA5Z", "ean_id": "7895389118629", "loja_id": 1, "preco": "R$323,00", "datahora": "16/01/2023 - 13:59:18"}, {"id": "01GPXRARKDFCNHVGMD08729Q2H", "ean_id": "7895389143065", "loja_id": 1, "preco": "R$75,00", "datahora": "16/01/2023 - 13:59:19"}, {"id": "01GPXRASMN6NPV93PT9EK0ECBV", "ean_id": "7895389156683", "loja_id": 1, "preco": "R$100,00", "datahora": "16/01/2023 - 13:59:20"}, {"id": "01GPXRAT496V1FGGAGF8YJSXC0", "ean_id": "7895389151398", "loja_id": 1, "preco": "R$49,90", "datahora": "16/01/2023 - 13:59:20"}, {"id": "01GPXRATGVPGD2ZAE1YMGWXXE3", "ean_id": "7895389161021", "loja_id": 1, "preco": "R$109,90", "datahora": "16/01/2023 - 13:59:20"}, {"id": "01GPXRATPQBQYJSPKDZ2GBERVC", "ean_id": "7895389137859", "loja_id": 1, "preco": "R$99,90", "datahora": "16/01/2023 - 13:59:21"}, {"id": "01GPXRAV2EPP39B65FTE7VNPJP", "ean_id": "7895389119985", "loja_id": 1, "preco": "R$228,00", "datahora": "16/01/2023 - 13:59:21"}, {"id": "01GPXRAVE6RT4CE3YKQTCAH01E", "ean_id": "7895389160390", "loja_id": 1, "preco": "R$239,00", "datahora": "16/01/2023 - 13:59:21"}, {"id": "01GPXRAVYK4D0F0QVKMHJ9R5M2", "ean_id": "7895389154627", "loja_id": 1, "preco": "R$152,90", "datahora": "16/01/2023 - 13:59:22"}, {"id": "01GPXRAWDQ5CFBN0413XA2Y9B3", "ean_id": "7895389137552", "loja_id": 1, "preco": "R$169,90", "datahora": "16/01/2023 - 13:59:22"}, {"id": "01GPXRAWSYWR7FFSER0D27GPQZ", "ean_id": "7895389138795", "loja_id": 1, "preco": "R$135,90", "datahora": "16/01/2023 - 13:59:23"}, {"id": "01GPXRAX9J154AX9KCESD1PS1T", "ean_id": "7895389138511", "loja_id": 1, "preco": "R$131,90", "datahora": "16/01/2023 - 13:59:23"}, {"id": "01GPXRAXNSJ5R75TGF9GXPYQYE", "ean_id": "7895389146448", "loja_id": 1, "preco": "R$239,90", "datahora": "16/01/2023 - 13:59:24"}, {"id": "01GPXRAY4YSEQ5GD6SS6QM0292", "ean_id": "7895389151671", "loja_id": 1, "preco": "R$59,00", "datahora": "16/01/2023 - 13:59:24"}, {"id": "01GPXRAY9AJY7Z02H7FB425KCH", "ean_id": "7895389142631", "loja_id": 1, "preco": "R$147,00", "datahora": "16/01/2023 - 13:59:24"}, {"id": "01GPXRAYWFJFM6ABBFRNQWYS22", "ean_id": "7895389138368", "loja_id": 1, "preco": "R$76,50", "datahora": "16/01/2023 - 13:59:25"}, {"id": "01GPXRAZ960ZD25K4ZAQVNKY2J", "ean_id": "7895389153712", "loja_id": 1, "preco": "R$18,50", "datahora": "16/01/2023 - 13:59:25"}, {"id": "01GPXRAZNQZEA3GKZ63V78BA2B", "ean_id": "7895389161625", "loja_id": 1, "preco": "R$107,10", "datahora": "16/01/2023 - 13:59:26"}], "lojas": [{"id": 1, "nome": "Dermage", "site": "htttps://www.dermage.com.br"}]}